yagdspy/__init__.py
yagdspy/eval_processing_graph.py
yagdspy/processing_module.py
yagdspy-1.0.dist-info/DESCRIPTION.rst
yagdspy-1.0.dist-info/METADATA
yagdspy-1.0.dist-info/RECORD
yagdspy-1.0.dist-info/WHEEL
yagdspy-1.0.dist-info/metadata.json
yagdspy-1.0.dist-info/top_level.txt
