Metadata-Version: 2.0
Name: yagdspy
Version: 1.0
Summary: Graph dependancy system for processing tasks
Home-page: https://github.com/krcurtis/yagdspy
Author: Keith Curtis
Author-email: UNKNOWN
License: License :: OSI Approved :: GNU Lesser General Public License v3 (LGPLv3)
Keywords: graph dependancy
Platform: UNKNOWN
Classifier: Development Status :: 4 - Beta
Classifier: License :: OSI Approved :: GNU Lesser General Public License v3 (LGPLv3)
Classifier: Programming Language :: Python :: 3.5
Requires-Python: >=3.5.3
Requires-Dist: pydot
